abgleich/__init__.py
abgleich/cli/__init__.py
abgleich/cli/_main_.py
abgleich/cli/backup.py
abgleich/cli/cleanup.py
abgleich/cli/compare.py
abgleich/cli/snap.py
abgleich/cli/tree.py
abgleich/cli/wizard.py
abgleich/core/__init__.py
abgleich/core/abc.py
abgleich/core/command.py
abgleich/core/comparisondataset.py
abgleich/core/comparisonitem.py
abgleich/core/comparisonzpool.py
abgleich/core/config.py
abgleich/core/configfield.py
abgleich/core/configspec.py
abgleich/core/dataset.py
abgleich/core/i18n.py
abgleich/core/io.py
abgleich/core/lib.py
abgleich/core/property.py
abgleich/core/snapshot.py
abgleich/core/transaction.py
abgleich/core/transactionlist.py
abgleich/core/transactionmeta.py
abgleich/core/zpool.py
abgleich/gui/__init__.py
abgleich/gui/abc.py
abgleich/gui/lib.py
abgleich/gui/transaction.py
abgleich/gui/wizard.py
abgleich/gui/wizard_base.py
abgleich/share/icon.svg
abgleich/share/translations.yaml
abgleich-0.0.8.dist-info/LICENSE
abgleich-0.0.8.dist-info/METADATA
abgleich-0.0.8.dist-info/WHEEL
abgleich-0.0.8.dist-info/entry_points.txt
abgleich-0.0.8.dist-info/top_level.txt
abgleich-0.0.8.dist-info/RECORD
