Metadata-Version: 2.1
Name: abgleich
Version: 0.0.8
Summary: zfs sync tool
Home-page: https://github.com/pleiszenburg/abgleich
Author: Sebastian M. Ernst
Author-email: ernst@pleiszenburg.de
License: LGPLv2
Download-URL: https://github.com/pleiszenburg/abgleich/archive/v0.0.8.tar.gz
Keywords: zfs,ssh
Platform: UNKNOWN
Classifier: Development Status :: 5 - Production/Stable
Classifier: Environment :: Console
Classifier: Environment :: X11 Applications
Classifier: Intended Audience :: Developers
Classifier: Intended Audience :: Education
Classifier: Intended Audience :: Information Technology
Classifier: Intended Audience :: Science/Research
Classifier: Intended Audience :: System Administrators
Classifier: License :: OSI Approved :: GNU Lesser General Public License v2 (LGPLv2)
Classifier: Operating System :: MacOS
Classifier: Operating System :: POSIX :: BSD
Classifier: Operating System :: POSIX :: Linux
Classifier: Programming Language :: Python :: 3
Classifier: Programming Language :: Python :: 3.6
Classifier: Programming Language :: Python :: 3.7
Classifier: Programming Language :: Python :: 3.8
Classifier: Programming Language :: Python :: 3.9
Classifier: Programming Language :: Python :: 3.10
Classifier: Programming Language :: Python :: 3 :: Only
Classifier: Programming Language :: Python :: Implementation :: CPython
Classifier: Topic :: Scientific/Engineering
Classifier: Topic :: System
Classifier: Topic :: System :: Archiving
Classifier: Topic :: System :: Archiving :: Backup
Classifier: Topic :: System :: Archiving :: Mirroring
Classifier: Topic :: System :: Filesystems
Classifier: Topic :: System :: Systems Administration
Classifier: Topic :: Utilities
Requires-Python: >=3.6
License-File: LICENSE
Requires-Dist: click
Requires-Dist: tabulate
Requires-Dist: pyyaml
Requires-Dist: typeguard
Provides-Extra: all
Requires-Dist: black ; extra == 'all'
Requires-Dist: setuptools ; extra == 'all'
Requires-Dist: python-language-server[all] ; extra == 'all'
Requires-Dist: pyqt5 ; extra == 'all'
Requires-Dist: twine ; extra == 'all'
Requires-Dist: wheel ; extra == 'all'
Provides-Extra: dev
Requires-Dist: black ; extra == 'dev'
Requires-Dist: python-language-server[all] ; extra == 'dev'
Requires-Dist: setuptools ; extra == 'dev'
Requires-Dist: twine ; extra == 'dev'
Requires-Dist: wheel ; extra == 'dev'
Provides-Extra: gui
Requires-Dist: pyqt5 ; extra == 'gui'
